devl/__init__.py
devl/main.py
devl-0.1.0.dist-info/LICENSE
devl-0.1.0.dist-info/METADATA
devl-0.1.0.dist-info/WHEEL
devl-0.1.0.dist-info/top_level.txt
devl-0.1.0.dist-info/RECORD
